auth0_oauth2/__about__.py
auth0_oauth2/__init__.py
auth0_oauth2/auth0.py
auth0_oauth2_backend-1.0.4.dist-info/LICENSE.txt
auth0_oauth2_backend-1.0.4.dist-info/METADATA
auth0_oauth2_backend-1.0.4.dist-info/WHEEL
auth0_oauth2_backend-1.0.4.dist-info/top_level.txt
auth0_oauth2_backend-1.0.4.dist-info/RECORD
