Metadata-Version: 2.1
Name: auth0_oauth2_backend
Version: 1.0.4
Summary: An Open edX Python Social Auth backend for Tutor Auth0
Home-page: https://github.com/blend-ed/auth0-oauth2-backend
Author: Zameel Hassan, zameel@blend-ed.com
Author-email: Zameel Hassan <zameel@blend-ed.com>
Project-URL: Homepage, https://github.com/blend-ed/auth0-oauth2-backend
Project-URL: Bug Tracker, https://github.com/blend-ed/auth0-oauth2-backend/issues
Keywords: Open edX,oauth,Auth0
Classifier: Programming Language :: Python :: 3
Classifier: License :: OSI Approved :: MIT License
Classifier: Operating System :: OS Independent
Requires-Python: >=3.10
License-File: LICENSE.txt
Requires-Dist: social-auth-core>=4.5.4
Requires-Dist: social-auth-app-django==5.4.2
